{"appleSKU":"","appleTeamID":"","enableCodelessAutoInitialization":true,"enableUnityGamingServicesAutoInitialization":false,"products":[{"id":"Bomb","type":1,"storeIDs":[],"defaultDescription":{"googleLocale":4,"title":"","description":""},"screenshotPath":"","applePriceTier":0,"googlePrice":{"data":[0,0,0,0],"num":0.0},"pricingTemplateID":"","descriptions":[],"udpPrice":{"data":[0,0,0,0],"num":0.0},"payouts":[{"t":"Other","st":"","q":0.0,"d":""}]},{"id":"Strawberry","type":1,"storeIDs":[],"defaultDescription":{"googleLocale":4,"title":"","description":""},"screenshotPath":"","applePriceTier":0,"googlePrice":{"data":[0,0,0,0],"num":0.0},"pricingTemplateID":"","descriptions":[],"udpPrice":{"data":[0,0,0,0],"num":0.0},"payouts":[]},{"id":"box.poop","type":0,"storeIDs":[],"defaultDescription":{"googleLocale":4,"title":"","description":""},"screenshotPath":"","applePriceTier":0,"googlePrice":{"data":[0,0,0,0],"num":0.0},"pricingTemplateID":"","descriptions":[],"udpPrice":{"data":[0,0,0,0],"num":0.0},"payouts":[]},{"id":"box.fart","type":0,"storeIDs":[],"defaultDescription":{"googleLocale":4,"title":"","description":""},"screenshotPath":"","applePriceTier":0,"googlePrice":{"data":[0,0,0,0],"num":0.0},"pricingTemplateID":"","descriptions":[],"udpPrice":{"data":[0,0,0,0],"num":0.0},"payouts":[]},{"id":"battlepass.isPremium","type":1,"storeIDs":[],"defaultDescription":{"googleLocale":4,"title":"","description":""},"screenshotPath":"","applePriceTier":0,"googlePrice":{"data":[0,0,0,0],"num":0.0},"pricingTemplateID":"","descriptions":[],"udpPrice":{"data":[0,0,0,0],"num":0.0},"payouts":[]}]}